{"cameraMode":{"drawMode":0,"name":"Shaded","section":"Shading Mode"},"sceneLighting":true,"audioPlay":false,"sceneViewState":{"m_AlwaysRefresh":false,"showFog":true,"showSkybox":true,"showFlares":true,"showImageEffects":true,"showParticleSystems":true,"showVisualEffectGraphs":true,"m_FxEnabled":true},"in2DMode":false,"pivot":{"x":382.3745422363281,"y":69.3445053100586,"z":-0.121337890625},"rotation":{"x":0.011999658308923245,"y":0.002999779535457492,"z":-0.00003599909177864902,"w":0.9999235272407532},"size":355.8322448730469,"orthographic":false}